paperkits/__init__.py
paper_kits-1.0.1.dist-info/LICENSE
paper_kits-1.0.1.dist-info/METADATA
paper_kits-1.0.1.dist-info/WHEEL
paper_kits-1.0.1.dist-info/top_level.txt
paper_kits-1.0.1.dist-info/RECORD
