Metadata-Version: 2.1
Name: paper-kits
Version: 1.0.1
Summary: Deep learning paper kits
Home-page: https://github.com/DengBoCong/nlp-paper
Author: DengBoCong
Author-email: bocongdeng@gmail.com
License: MIT License
Project-URL: Bug Reports, https://github.com/DengBoCong/nlp-paper/issues
Project-URL: Funding, https://pypi.org/project/paper-kits/
Project-URL: Source, https://github.com/DengBoCong/nlp-paper
Keywords: paper,nlp,deep learning,kits
Platform: UNKNOWN
Classifier: Programming Language :: Python :: 3
Classifier: Programming Language :: Python :: 3.7
Classifier: Programming Language :: Python :: 3.8
Classifier: License :: OSI Approved :: MIT License
Classifier: Operating System :: OS Independent
License-File: LICENSE
Requires-Dist: jieba (==0.42.1)
Requires-Dist: PyQt6 (==6.3.0)
